setup.py
restcountries_py/__init__.py
restcountries_py/country.py
restcountries_py/restcountry.py
restcountries_py.egg-info/PKG-INFO
restcountries_py.egg-info/SOURCES.txt
restcountries_py.egg-info/dependency_links.txt
restcountries_py.egg-info/requires.txt
restcountries_py.egg-info/top_level.txt