Metadata-Version: 1.1
Name: restcountries-py
Version: v0.1
Summary: A Python wrapper for Restcountries API provided by https://restcountries.eu
Home-page: https://github.com/99darshan/restcountries_py
Author: Darshan Adhikari
Author-email: dsn.adh@hotmail.com
License: UNKNOWN
Download-URL: https://github.com/99darshan/restcountries_py/tarball/v0.1
Keywords: countries,rest countries,wrapper,database,api
Platform: UNKNOWN
Classifier: Development Status :: 4 - Beta
Classifier: Intended Audience :: Developers
Classifier: Operating System :: OS Independent
Classifier: Programming Language :: Python :: 3
Classifier: Programming Language :: Python :: 3.3
Classifier: Programming Language :: Python :: 3.4
Classifier: Topic :: Utilities
Classifier: License :: OSI Approved :: MIT License
